LICENSE
MANIFEST.in
README.md
pyproject.toml
setup.cfg
setup.py
sepl_light_lib/__init__.py
sepl_light_lib/color.py
sepl_light_lib/const.py
sepl_light_lib/pkginfo.py
sepl_light_lib/wave.py
sepl_light_lib.egg-info/PKG-INFO
sepl_light_lib.egg-info/SOURCES.txt
sepl_light_lib.egg-info/dependency_links.txt
sepl_light_lib.egg-info/not-zip-safe
sepl_light_lib.egg-info/top_level.txt
src/extension.c
src/wave/wave_module.c
src/wave/wave_module.h
src/wave/components/cie_rgb.c
src/wave/components/cie_rgb.h