Metadata-Version: 2.1
Name: sepl-light-lib
Version: 0.0.4
Summary: Library for convenient work with interference phenomena
Home-page: https://github.com/Sersoid/SEPL-Light-Lib
Author: Sersoid
License: MIT
Classifier: Development Status :: 3 - Alpha
Classifier: License :: OSI Approved :: MIT License
Classifier: Programming Language :: C
Classifier: Programming Language :: Python
Classifier: Programming Language :: Python :: 3
License-File: LICENSE
